README.rst
setup.py
atcodes_chappie.egg-info/PKG-INFO
atcodes_chappie.egg-info/SOURCES.txt
atcodes_chappie.egg-info/dependency_links.txt
atcodes_chappie.egg-info/requires.txt
atcodes_chappie.egg-info/top_level.txt
chappie/__init__.py
chappie/client/__init__.py
chappie/client/file_manager.py
chappie/client/log_notifier.py
chappie/client/message_manager.py
chappie/client/aws/__init__.py
chappie/client/aws/s3_client.py
chappie/client/aws/sns_client.py
chappie/client/local/__init__.py
chappie/client/local/local_client.py
chappie/client/local/localstack_sns_client.py
chappie/client/rollbar/__init__.py
chappie/client/rollbar/rollbar_notifier.py
chappie/client/sentry/__init__.py
chappie/client/sentry/sentry_notifier.py
chappie/config/datefinder.yaml
chappie/utils/__init__.py
chappie/utils/date_finder.py
chappie/utils/db_tools.py
chappie/utils/dict_tools.py
chappie/utils/file_tools.py
chappie/utils/list_tools.py
chappie/utils/local_file_adapter.py
chappie/utils/numeric_parser.py
chappie/utils/random_value.py
chappie/utils/request_tools.py
chappie/utils/text_tools.py
chappie/utils/timer_tools.py
tests/client/__init__.py
tests/client/test_file_manager.py
tests/client/aws/__init__.py
tests/client/aws/test_s3_client.py
tests/client/local/__init__.py
tests/client/local/test_local_client.py
tests/utils/__init__.py
tests/utils/test_date_finder.py
tests/utils/test_dict_tools.py
tests/utils/test_file_tools.py
tests/utils/test_text_tools.py