Metadata-Version: 2.1
Name: atcodes-chappie
Version: 0.1.5
Summary: A collection of tools and utilities commonly for python projects.
Home-page: https://github.com/atcodesco/chappie/
Author: ATCODES Dev Team
Author-email: admin@atcodes.co
License: MIT
Keywords: utilities clients
Platform: UNKNOWN
Classifier: Development Status :: 3 - Alpha
Classifier: Intended Audience :: Developers
Classifier: License :: OSI Approved :: MIT License
Classifier: Programming Language :: Python :: 3.6
Provides-Extra: dev
Provides-Extra: test
